fels/__init__.py
fels/fels.py
fels/landsat.py
fels/sentinel2.py
fels/utils.py
fels/data/WRS2_descending.cpg
fels/data/WRS2_descending.dbf
fels/data/WRS2_descending.prj
fels/data/WRS2_descending.sbn
fels/data/WRS2_descending.sbx
fels/data/WRS2_descending.shp
fels/data/WRS2_descending.shx
fels/data/WRS2_descending.xml
fels/data/sentinel_2_index_shapefile.cpg
fels/data/sentinel_2_index_shapefile.dbf
fels/data/sentinel_2_index_shapefile.prj
fels/data/sentinel_2_index_shapefile.sbn
fels/data/sentinel_2_index_shapefile.sbx
fels/data/sentinel_2_index_shapefile.shp
fels/data/sentinel_2_index_shapefile.shx
fels/data/source_metadata.txt
FeLS-1.4.0.dist-info/LICENSE
FeLS-1.4.0.dist-info/METADATA
FeLS-1.4.0.dist-info/WHEEL
FeLS-1.4.0.dist-info/dependency_links.txt
FeLS-1.4.0.dist-info/entry_points.txt
FeLS-1.4.0.dist-info/top_level.txt
FeLS-1.4.0.dist-info/RECORD
