Metadata-Version: 2.1
Name: FeLS
Version: 1.4.0
Summary: Fetch Landsat & Sentinel Data from google cloud
Home-page: https://github.com/vascobnunes/fetchLandsatSentinelFromGoogleCloud
Author: vascobnunes
Author-email: vascobnunes@gmail.com
License: GPL
Platform: UNKNOWN
Requires-Dist: numpy
Requires-Dist: requests
Requires-Dist: shapely
Requires-Dist: geopandas
